Workbook

Sheet 首頁
A1: 破產計算機 · 貸款利息試算表（公式可改） | K1: v6a-chart-dynamic-presets | AD1: principal_list | AE1: income_list
A2: 【 輸入區 】B 欄 ▾ 下拉；C/D ± 微調；右側圖表（最長 50 年） | AD2: 5000000 | AE2: 50000
A3: 貸款模式 | E3: xlsm：點選左側六顆色按鈕一鍵套用（機車／汽車／信貸／房貸／學貸／裝潢） | AD3: 5500000 | AE3: 55000
A4: 輸入參數 | H4: 參數總覽 | AD4: 6000000 | AE4: 60000
A5: 項目 | B5: ▾ 可選 | C5: + | D5: − | E5: 單位 | F5: 說明 | H5: 摘要 | I5: 數值 | AD5: 6500000 | AE5: 65000
A6: 貸款本金 | B6: 12000000 | C6: + | D6: - | E6: NT$ | F6: 可輸入或 B 欄下拉快選 | H6: 貸款本金 | I6: =B6 | AD6: 7000000 | AE6: 70000
A7: 年利率 | B7: 2.2 | C7: + | D7: - | E7: % | F7: 例：2.2；可下拉 | H7: 年利率 | I7: =TEXT(B7,"0.00")&"%" | AD7: 7500000 | AE7: 75000
A8: 貸款年期 | B8: 30 | C8: + | D8: - | E8: 年 | F8: 可下拉 5～50 年 | H8: 貸款年期 | I8: =TEXT(B8,"0")&" 年" | AD8: 8000000 | AE8: 80000
A9: 月收入（預警） | B9: 80000 | C9: + | D9: - | E9: NT$ | F9: 算 DTI 用 | H9: 月收入（預警） | I9: =B9 | AD9: 8500000 | AE9: 85000
AD10: 9000000 | AE10: 90000
A11: 試算結果 | H11: 資金總覽 | AD11: 9500000 | AE11: 95000
A12: 項目 | B12: 結果 | E12: 單位 | F12: 公式說明 | H12: 摘要 | I12: 數值 | AD12: 10000000 | AE12: 100000
A13: ▸ 本息均攤 · 每期明細 | B13: =PMT(B7/12/100,B8*12,-B6) | E13: NT$ | H13: 本息均攤 · 每月繳款 | I13: =B13 | AD13: 10500000 | AE13: 105000
A14: ▸ 本金平均 · 每期明細 | B14: =B6*(B7/12/100)+B6/(B8*12) | E14: NT$ | H14: 本金平均 · 首期月付 | I14: =B14 | AD14: 11000000 | AE14: 110000
A15: 本息均攤 · 總繳利息 | B15: =B13*B8*12-B6 | E15: NT$ | F15: 總付款－本金 | H15: 總繳金額 | I15: =B6+B15 | AD15: 11500000 | AE15: 115000
A16: DTI 債務收入比 | B16: =IF(B9=0,0,B13/B9) | E16: % | F16: 月付÷月收入；<35% 安全；≥50% 預警 | H16: 利息佔本金比例 | I16: =IF(B6=0,0,B15/B6) | AD16: 12000000 | AE16: 120000
A17: =IF(B16>=0.5,"⚠ 財務健康狀態｜破產預警：先降月付或提高收入",IF(B16>=0.35,"⚠ 財務健康狀態｜壓力偏高：月付偏緊，建議調整貸款條件","✓ 財務健康狀態｜安全區：現金流尚可")) | AD17: 12500000 | AE17: 125000
A18: （試算結果僅供參考，實際以銀行／法令為準；負債比建議＜35%，≥50% 為破產預警。） | AD18: 13000000 | AE18: 130000
AD19: 13500000 | AE19: 135000
AD20: 14000000 | AE20: 140000
AD21: 14500000 | AE21: 145000
AD22: 15000000 | AE22: 150000
AD23: 15500000 | AE23: 155000
AD24: 16000000 | AE24: 160000
AD25: 16500000 | AE25: 165000
AD26: 17000000 | AE26: 170000
AD27: 17500000 | AE27: 175000
AD28: 18000000 | AE28: 180000
AD29: 18500000 | AE29: 185000
AD30: 19000000 | AE30: 190000
... AD42: 25000000 | AE42: 250000

Sheet 本息均攤
A1: ← 回首頁 | B1: 本息均攤 · 每期繳款明細（連動首頁 B 欄） | G1: annuity
A2: 右側視窗：【檢視】→【新建視窗】→【並排顯示】→ 拖曳此視窗到螢幕右邊｜改首頁 B6～B8 後此表自動重算
A3: 期數 | B3: 每期還款 | C3: 每期利息 | D3: 每期本金 | E3: 剩餘本金
A4: =IF((ROW()-3)<=('首頁'!$B$8*12),ROW()-3,"") | B4: =IF((ROW()-3)<=('首頁'!$B$8*12),C4+D4,"") | C4: =IF((ROW()-3)<=('首頁'!$B$8*12),G4*'首頁'!$B$7/12/100,"") | D4: =IF((ROW()-3)<=('首頁'!$B$8*12),IF(ROW()-3=('首頁'!$B$8*12),G4,MIN(G4,'首頁'!$B$13-C4)),"") | E4: =IF((ROW()-3)<=('首頁'!$B$8*12),G4-D4,"") | G4: =IF((ROW()-3)<=('首頁'!$B$8*12),'首頁'!$B$6,"")
A5: =IF((ROW()-3)<=('首頁'!$B$8*12),ROW()-3,"") | B5: =IF((ROW()-3)<=('首頁'!$B$8*12),C5+D5,"") | C5: =IF((ROW()-3)<=('首頁'!$B$8*12),G5*'首頁'!$B$7/12/100,"") | D5: =IF((ROW()-3)<=('首頁'!$B$8*12),IF(ROW()-3=('首頁'!$B$8*12),G5,MIN(G5,'首頁'!$B$13-C5)),"") | E5: =IF((ROW()-3)<=('首頁'!$B$8*12),G5-D5,"") | G5: =IF((ROW()-3)<=('首頁'!$B$8*12),E4,"")
A6: =IF((ROW()-3)<=('首頁'!$B$8*12),ROW()-3,"") | B6: =IF((ROW()-3)<=('首頁'!$B$8*12),C6+D6,"") | C6: =IF((ROW()-3)<=('首頁'!$B$8*12),G6*'首頁'!$B$7/12/100,"") | D6: =IF((ROW()-3)<=('首頁'!$B$8*12),IF(ROW()-3=('首頁'!$B$8*12),G6,MIN(G6,'首頁'!$B$13-C6)),"") | E6: =IF((ROW()-3)<=('首頁'!$B$8*12),G6-D6,"") | G6: =IF((ROW()-3)<=('首頁'!$B$8*12),E5,"")
A7: =IF((ROW()-3)<=('首頁'!$B$8*12),ROW()-3,"") | B7: =IF((ROW()-3)<=('首頁'!$B$8*12),C7+D7,"") | C7: =IF((ROW()-3)<=('首頁'!$B$8*12),G7*'首頁'!$B$7/12/100,"") | D7: =IF((ROW()-3)<=('首頁'!$B$8*12),IF(ROW()-3=('首頁'!$B$8*12),G7,MIN(G7,'首頁'!$B$13-C7)),"") | E7: =IF((ROW()-3)<=('首頁'!$B$8*12),G7-D7,"") | G7: =IF((ROW()-3)<=('首頁'!$B$8*12),E6,"")
A8: =IF((ROW()-3)<=('首頁'!$B$8*12),ROW()-3,"") | B8: =IF((ROW()-3)<=('首頁'!$B$8*12),C8+D8,"") | C8: =IF((ROW()-3)<=('首頁'!$B$8*12),G8*'首頁'!$B$7/12/100,"") | D8: =IF((ROW()-3)<=('首頁'!$B$8*12),IF(ROW()-3=('首頁'!$B$8*12),G8,MIN(G8,'首頁'!$B$13-C8)),"") | E8: =IF((ROW()-3)<=('首頁'!$B$8*12),G8-D8,"") | G8: =IF((ROW()-3)<=('首頁'!$B$8*12),E7,"")
A9: =IF((ROW()-3)<=('首頁'!$B$8*12),ROW()-3,"") | B9: =IF((ROW()-3)<=('首頁'!$B$8*12),C9+D9,"") | C9: =IF((ROW()-3)<=('首頁'!$B$8*12),G9*'首頁'!$B$7/12/100,"") | D9: =IF((ROW()-3)<=('首頁'!$B$8*12),IF(ROW()-3=('首頁'!$B$8*12),G9,MIN(G9,'首頁'!$B$13-C9)),"") | E9: =IF((ROW()-3)<=('首頁'!$B$8*12),G9-D9,"") | G9: =IF((ROW()-3)<=('首頁'!$B$8*12),E8,"")
A10: =IF((ROW()-3)<=('首頁'!$B$8*12),ROW()-3,"") | B10: =IF((ROW()-3)<=('首頁'!$B$8*12),C10+D10,"") | C10: =IF((ROW()-3)<=('首頁'!$B$8*12),G10*'首頁'!$B$7/12/100,"") | D10: =IF((ROW()-3)<=('首頁'!$B$8*12),IF(ROW()-3=('首頁'!$B$8*12),G10,MIN(G10,'首頁'!$B$13-C10)),"") | E10: =IF((ROW()-3)<=('首頁'!$B$8*12),G10-D10,"") | G10: =IF((ROW()-3)<=('首頁'!$B$8*12),E9,"")
A11: =IF((ROW()-3)<=('首頁'!$B$8*12),ROW()-3,"") | B11: =IF((ROW()-3)<=('首頁'!$B$8*12),C11+D11,"") | C11: =IF((ROW()-3)<=('首頁'!$B$8*12),G11*'首頁'!$B$7/12/100,"") | D11: =IF((ROW()-3)<=('首頁'!$B$8*12),IF(ROW()-3=('首頁'!$B$8*12),G11,MIN(G11,'首頁'!$B$13-C11)),"") | E11: =IF((ROW()-3)<=('首頁'!$B$8*12),G11-D11,"") | G11: =IF((ROW()-3)<=('首頁'!$B$8*12),E10,"")
A12: =IF((ROW()-3)<=('首頁'!$B$8*12),ROW()-3,"") | B12: =IF((ROW()-3)<=('首頁'!$B$8*12),C12+D12,"") | C12: =IF((ROW()-3)<=('首頁'!$B$8*12),G12*'首頁'!$B$7/12/100,"") | D12: =IF((ROW()-3)<=('首頁'!$B$8*12),IF(ROW()-3=('首頁'!$B$8*12),G12,MIN(G12,'首頁'!$B$13-C12)),"") | E12: =IF((ROW()-3)<=('首頁'!$B$8*12),G12-D12,"") | G12: =IF((ROW()-3)<=('首頁'!$B$8*12),E11,"")
A13: =IF((ROW()-3)<=('首頁'!$B$8*12),ROW()-3,"") | B13: =IF((ROW()-3)<=('首頁'!$B$8*12),C13+D13,"") | C13: =IF((ROW()-3)<=('首頁'!$B$8*12),G13*'首頁'!$B$7/12/100,"") | D13: =IF((ROW()-3)<=('首頁'!$B$8*12),IF(ROW()-3=('首頁'!$B$8*12),G13,MIN(G13,'首頁'!$B$13-C13)),"") | E13: =IF((ROW()-3)<=('首頁'!$B$8*12),G13-D13,"") | G13: =IF((ROW()-3)<=('首頁'!$B$8*12),E12,"")
A14: =IF((ROW()-3)<=('首頁'!$B$8*12),ROW()-3,"") | B14: =IF((ROW()-3)<=('首頁'!$B$8*12),C14+D14,"") | C14: =IF((ROW()-3)<=('首頁'!$B$8*12),G14*'首頁'!$B$7/12/100,"") | D14: =IF((ROW()-3)<=('首頁'!$B$8*12),IF(ROW()-3=('首頁'!$B$8*12),G14,MIN(G14,'首頁'!$B$13-C14)),"") | E14: =IF((ROW()-3)<=('首頁'!$B$8*12),G14-D14,"") | G14: =IF((ROW()-3)<=('首頁'!$B$8*12),E13,"")
A15: =IF((ROW()-3)<=('首頁'!$B$8*12),ROW()-3,"") | B15: =IF((ROW()-3)<=('首頁'!$B$8*12),C15+D15,"") | C15: =IF((ROW()-3)<=('首頁'!$B$8*12),G15*'首頁'!$B$7/12/100,"") | D15: =IF((ROW()-3)<=('首頁'!$B$8*12),IF(ROW()-3=('首頁'!$B$8*12),G15,MIN(G15,'首頁'!$B$13-C15)),"") | E15: =IF((ROW()-3)<=('首頁'!$B$8*12),G15-D15,"") | G15: =IF((ROW()-3)<=('首頁'!$B$8*12),E14,"")
A16: =IF((ROW()-3)<=('首頁'!$B$8*12),ROW()-3,"") | B16: =IF((ROW()-3)<=('首頁'!$B$8*12),C16+D16,"") | C16: =IF((ROW()-3)<=('首頁'!$B$8*12),G16*'首頁'!$B$7/12/100,"") | D16: =IF((ROW()-3)<=('首頁'!$B$8*12),IF(ROW()-3=('首頁'!$B$8*12),G16,MIN(G16,'首頁'!$B$13-C16)),"") | E16: =IF((ROW()-3)<=('首頁'!$B$8*12),G16-D16,"") | G16: =IF((ROW()-3)<=('首頁'!$B$8*12),E15,"")
... A603: =IF((ROW()-3)<=('首頁'!$B$8*12),ROW()-3,"") | B603: =IF((ROW()-3)<=('首頁'!$B$8*12),C603+D603,"") | C603: =IF((ROW()-3)<=('首頁'!$B$8*12),G603*'首頁'!$B$7/12/100,"") | D603: =IF((ROW()-3)<=('首頁'!$B$8*12),IF(ROW()-3=('首頁'!$B$8*12),G603,MIN(G603,'首頁'!$B$13-C603)),"") | E603: =IF((ROW()-3)<=('首頁'!$B$8*12),G603-D603,"") | G603: =IF((ROW()-3)<=('首頁'!$B$8*12),E602,"")

Sheet 本金平均
A1: ← 回首頁 | B1: 本金平均 · 每期繳款明細（連動首頁 B 欄） | G1: equalPrincipal
A2: 右側視窗：【檢視】→【新建視窗】→【並排顯示】→ 拖曳此視窗到螢幕右邊｜改首頁 B6～B8 後此表自動重算
A3: 期數 | B3: 每期還款 | C3: 每期利息 | D3: 每期本金 | E3: 剩餘本金
A4: =IF((ROW()-3)<=('首頁'!$B$8*12),ROW()-3,"") | B4: =IF((ROW()-3)<=('首頁'!$B$8*12),C4+D4,"") | C4: =IF((ROW()-3)<=('首頁'!$B$8*12),G4*'首頁'!$B$7/12/100,"") | D4: =IF((ROW()-3)<=('首頁'!$B$8*12),IF(ROW()-3=('首頁'!$B$8*12),G4,MIN(G4,'首頁'!$B$6/('首頁'!$B$8*12))),"") | E4: =IF((ROW()-3)<=('首頁'!$B$8*12),G4-D4,"") | G4: =IF((ROW()-3)<=('首頁'!$B$8*12),'首頁'!$B$6,"")
A5: =IF((ROW()-3)<=('首頁'!$B$8*12),ROW()-3,"") | B5: =IF((ROW()-3)<=('首頁'!$B$8*12),C5+D5,"") | C5: =IF((ROW()-3)<=('首頁'!$B$8*12),G5*'首頁'!$B$7/12/100,"") | D5: =IF((ROW()-3)<=('首頁'!$B$8*12),IF(ROW()-3=('首頁'!$B$8*12),G5,MIN(G5,'首頁'!$B$6/('首頁'!$B$8*12))),"") | E5: =IF((ROW()-3)<=('首頁'!$B$8*12),G5-D5,"") | G5: =IF((ROW()-3)<=('首頁'!$B$8*12),E4,"")
A6: =IF((ROW()-3)<=('首頁'!$B$8*12),ROW()-3,"") | B6: =IF((ROW()-3)<=('首頁'!$B$8*12),C6+D6,"") | C6: =IF((ROW()-3)<=('首頁'!$B$8*12),G6*'首頁'!$B$7/12/100,"") | D6: =IF((ROW()-3)<=('首頁'!$B$8*12),IF(ROW()-3=('首頁'!$B$8*12),G6,MIN(G6,'首頁'!$B$6/('首頁'!$B$8*12))),"") | E6: =IF((ROW()-3)<=('首頁'!$B$8*12),G6-D6,"") | G6: =IF((ROW()-3)<=('首頁'!$B$8*12),E5,"")
A7: =IF((ROW()-3)<=('首頁'!$B$8*12),ROW()-3,"") | B7: =IF((ROW()-3)<=('首頁'!$B$8*12),C7+D7,"") | C7: =IF((ROW()-3)<=('首頁'!$B$8*12),G7*'首頁'!$B$7/12/100,"") | D7: =IF((ROW()-3)<=('首頁'!$B$8*12),IF(ROW()-3=('首頁'!$B$8*12),G7,MIN(G7,'首頁'!$B$6/('首頁'!$B$8*12))),"") | E7: =IF((ROW()-3)<=('首頁'!$B$8*12),G7-D7,"") | G7: =IF((ROW()-3)<=('首頁'!$B$8*12),E6,"")
A8: =IF((ROW()-3)<=('首頁'!$B$8*12),ROW()-3,"") | B8: =IF((ROW()-3)<=('首頁'!$B$8*12),C8+D8,"") | C8: =IF((ROW()-3)<=('首頁'!$B$8*12),G8*'首頁'!$B$7/12/100,"") | D8: =IF((ROW()-3)<=('首頁'!$B$8*12),IF(ROW()-3=('首頁'!$B$8*12),G8,MIN(G8,'首頁'!$B$6/('首頁'!$B$8*12))),"") | E8: =IF((ROW()-3)<=('首頁'!$B$8*12),G8-D8,"") | G8: =IF((ROW()-3)<=('首頁'!$B$8*12),E7,"")
A9: =IF((ROW()-3)<=('首頁'!$B$8*12),ROW()-3,"") | B9: =IF((ROW()-3)<=('首頁'!$B$8*12),C9+D9,"") | C9: =IF((ROW()-3)<=('首頁'!$B$8*12),G9*'首頁'!$B$7/12/100,"") | D9: =IF((ROW()-3)<=('首頁'!$B$8*12),IF(ROW()-3=('首頁'!$B$8*12),G9,MIN(G9,'首頁'!$B$6/('首頁'!$B$8*12))),"") | E9: =IF((ROW()-3)<=('首頁'!$B$8*12),G9-D9,"") | G9: =IF((ROW()-3)<=('首頁'!$B$8*12),E8,"")
A10: =IF((ROW()-3)<=('首頁'!$B$8*12),ROW()-3,"") | B10: =IF((ROW()-3)<=('首頁'!$B$8*12),C10+D10,"") | C10: =IF((ROW()-3)<=('首頁'!$B$8*12),G10*'首頁'!$B$7/12/100,"") | D10: =IF((ROW()-3)<=('首頁'!$B$8*12),IF(ROW()-3=('首頁'!$B$8*12),G10,MIN(G10,'首頁'!$B$6/('首頁'!$B$8*12))),"") | E10: =IF((ROW()-3)<=('首頁'!$B$8*12),G10-D10,"") | G10: =IF((ROW()-3)<=('首頁'!$B$8*12),E9,"")
A11: =IF((ROW()-3)<=('首頁'!$B$8*12),ROW()-3,"") | B11: =IF((ROW()-3)<=('首頁'!$B$8*12),C11+D11,"") | C11: =IF((ROW()-3)<=('首頁'!$B$8*12),G11*'首頁'!$B$7/12/100,"") | D11: =IF((ROW()-3)<=('首頁'!$B$8*12),IF(ROW()-3=('首頁'!$B$8*12),G11,MIN(G11,'首頁'!$B$6/('首頁'!$B$8*12))),"") | E11: =IF((ROW()-3)<=('首頁'!$B$8*12),G11-D11,"") | G11: =IF((ROW()-3)<=('首頁'!$B$8*12),E10,"")
A12: =IF((ROW()-3)<=('首頁'!$B$8*12),ROW()-3,"") | B12: =IF((ROW()-3)<=('首頁'!$B$8*12),C12+D12,"") | C12: =IF((ROW()-3)<=('首頁'!$B$8*12),G12*'首頁'!$B$7/12/100,"") | D12: =IF((ROW()-3)<=('首頁'!$B$8*12),IF(ROW()-3=('首頁'!$B$8*12),G12,MIN(G12,'首頁'!$B$6/('首頁'!$B$8*12))),"") | E12: =IF((ROW()-3)<=('首頁'!$B$8*12),G12-D12,"") | G12: =IF((ROW()-3)<=('首頁'!$B$8*12),E11,"")
A13: =IF((ROW()-3)<=('首頁'!$B$8*12),ROW()-3,"") | B13: =IF((ROW()-3)<=('首頁'!$B$8*12),C13+D13,"") | C13: =IF((ROW()-3)<=('首頁'!$B$8*12),G13*'首頁'!$B$7/12/100,"") | D13: =IF((ROW()-3)<=('首頁'!$B$8*12),IF(ROW()-3=('首頁'!$B$8*12),G13,MIN(G13,'首頁'!$B$6/('首頁'!$B$8*12))),"") | E13: =IF((ROW()-3)<=('首頁'!$B$8*12),G13-D13,"") | G13: =IF((ROW()-3)<=('首頁'!$B$8*12),E12,"")
A14: =IF((ROW()-3)<=('首頁'!$B$8*12),ROW()-3,"") | B14: =IF((ROW()-3)<=('首頁'!$B$8*12),C14+D14,"") | C14: =IF((ROW()-3)<=('首頁'!$B$8*12),G14*'首頁'!$B$7/12/100,"") | D14: =IF((ROW()-3)<=('首頁'!$B$8*12),IF(ROW()-3=('首頁'!$B$8*12),G14,MIN(G14,'首頁'!$B$6/('首頁'!$B$8*12))),"") | E14: =IF((ROW()-3)<=('首頁'!$B$8*12),G14-D14,"") | G14: =IF((ROW()-3)<=('首頁'!$B$8*12),E13,"")
A15: =IF((ROW()-3)<=('首頁'!$B$8*12),ROW()-3,"") | B15: =IF((ROW()-3)<=('首頁'!$B$8*12),C15+D15,"") | C15: =IF((ROW()-3)<=('首頁'!$B$8*12),G15*'首頁'!$B$7/12/100,"") | D15: =IF((ROW()-3)<=('首頁'!$B$8*12),IF(ROW()-3=('首頁'!$B$8*12),G15,MIN(G15,'首頁'!$B$6/('首頁'!$B$8*12))),"") | E15: =IF((ROW()-3)<=('首頁'!$B$8*12),G15-D15,"") | G15: =IF((ROW()-3)<=('首頁'!$B$8*12),E14,"")
A16: =IF((ROW()-3)<=('首頁'!$B$8*12),ROW()-3,"") | B16: =IF((ROW()-3)<=('首頁'!$B$8*12),C16+D16,"") | C16: =IF((ROW()-3)<=('首頁'!$B$8*12),G16*'首頁'!$B$7/12/100,"") | D16: =IF((ROW()-3)<=('首頁'!$B$8*12),IF(ROW()-3=('首頁'!$B$8*12),G16,MIN(G16,'首頁'!$B$6/('首頁'!$B$8*12))),"") | E16: =IF((ROW()-3)<=('首頁'!$B$8*12),G16-D16,"") | G16: =IF((ROW()-3)<=('首頁'!$B$8*12),E15,"")
... A603: =IF((ROW()-3)<=('首頁'!$B$8*12),ROW()-3,"") | B603: =IF((ROW()-3)<=('首頁'!$B$8*12),C603+D603,"") | C603: =IF((ROW()-3)<=('首頁'!$B$8*12),G603*'首頁'!$B$7/12/100,"") | D603: =IF((ROW()-3)<=('首頁'!$B$8*12),IF(ROW()-3=('首頁'!$B$8*12),G603,MIN(G603,'首頁'!$B$6/('首頁'!$B$8*12))),"") | E603: =IF((ROW()-3)<=('首頁'!$B$8*12),G603-D603,"") | G603: =IF((ROW()-3)<=('首頁'!$B$8*12),E602,"")
